timeseries_generator/__init__.py
timeseries_generator/base_factor.py
timeseries_generator/errors.py
timeseries_generator/generator.py
timeseries_generator/holiday_factor.py
timeseries_generator/linear_trend.py
timeseries_generator/random_feature_factor.py
timeseries_generator/sinusoidal_factor.py
timeseries_generator/utils.py
timeseries_generator/weekday_factor.py
timeseries_generator/white_noise.py
timeseries_generator/external_factors/__init__.py
timeseries_generator/external_factors/country_gdp_factor.py
timeseries_generator/external_factors/eu_industry_product_factor.py
timeseries_generator/external_factors/external_factor.py
timeseries_generator/resources/public_data/GDP_per_capita_countries.csv
timeseries_generator/resources/public_data/eu_prod_index.csv
timeseries_generator-0.1.0.dist-info/LICENSE
timeseries_generator-0.1.0.dist-info/METADATA
timeseries_generator-0.1.0.dist-info/WHEEL
timeseries_generator-0.1.0.dist-info/top_level.txt
timeseries_generator-0.1.0.dist-info/RECORD
