Metadata-Version: 2.1
Name: timeseries-generator
Version: 0.1.0
Summary: Library for generating time series data
Home-page: https://github.com/Nike-Inc/ts-generator
Author: Zhe Sun, Jaap Langemeijer
Author-email: zhe.sun@nike.com
License: Apache License, v2.0
Platform: UNKNOWN
Classifier: Programming Language :: Python :: 3
Classifier: Operating System :: OS Independent
Requires-Python: >=3.6
License-File: LICENSE
Requires-Dist: pandas (==1.2.0)
Requires-Dist: workalendar (==15.0.1)
Requires-Dist: matplotlib (==3.3.3)
